Workbook

Sheet Instructions
A1: Eternal Limited (formerly Zomato) – Professional Dynamic DCF Model
A3: Purpose
A4: Five-year unlevered DCF with editable assumptions, operating-driver revenue build, EBITDA bridge, FCFF, WACC, terminal value and valuation sensitivity.
A6: How to use
A7: • Edit only the yellow cells on the Assumptions sheet.
A8: • Review Revenue Build and Operating Model to understand the operating drivers.
A9: • DCF calculates FCFF, enterprise value, equity value and DCF value per share.
A10: • Sensitivity tests WACC and terminal growth.
A11: • All amounts are ₹ crore except per-share values and percentages.
A14: Model architecture
A15: Assumptions → Revenue Build → Operating Model → DCF → Sensitivity. Yellow cells are hardcoded inputs; blue/white cells are formulas.
A17: Important modelling note
... A20: Selected reference points
A21: Metric | B21: Reference
A22: FY26 revenue from operations | B22: ₹54,364 crore
A23: FY26 cash balance | B23: ₹17,972 crore
A24: Q4 FY26 food-delivery NOV | B24: ₹9,757 crore; +18.8% YoY
A25: Q4 FY26 quick-commerce NOV | B25: ₹14,386 crore; +95.4% YoY
A26: Q4 FY26 food-delivery adjusted EBITDA margin | B26: 5.5% of NOV
A27: Q4 FY26 Blinkit adjusted EBITDA | B27: ₹37 crore; positive

Sheet Assumptions
A1: Assumptions
A3: Operating assumptions | B3: FY26A / Current | C3: FY27E | D3: FY28E | E3: FY29E | F3: FY30E | G3: FY31E | H3: Logic
A4: Food delivery NOV (₹ cr) | B4: 39000 | C4: 46800 | D4: 56160 | E4: 66110 | F4: 77110 | G4: 88680 | H4: Base NOV × growth
A5: Food delivery NOV growth | C5: 0.2 | D5: 0.2 | E5: 0.177 | F5: 0.166 | G5: 0.15 | H5: Maturity reduces growth
A6: Food delivery take rate | B6: 0.269 | C6: 0.27 | D6: 0.27 | E6: 0.27 | F6: 0.27 | G6: 0.27 | H6: Commission + platform fee + ads
A7: Quick commerce NOV (₹ cr) | B7: 47000 | C7: 75200 | D7: 120320 | E7: 180480 | F7: 252672 | G7: 315840 | H7: Base NOV × growth
A8: Quick commerce NOV growth | C8: 0.6 | D8: 0.6 | E8: 0.5 | F8: 0.4 | G8: 0.25 | H8: High growth, then normalisation
A9: Quick commerce gross monetisation | B9: 0.28 | C9: 0.28 | D9: 0.285 | E9: 0.29 | F9: 0.29 | G9: 0.29 | H9: Gross profit + ads + fees as % NOV
A10: Other revenue (₹ cr) | B10: 4364 | C10: 4800 | D10: 5280 | E10: 5808 | F10: 6389 | G10: 7028 | H10: Adjacent businesses
A11: Other revenue growth | C11: 0.1 | D11: 0.1 | E11: 0.1 | F11: 0.1 | G11: 0.1 | H11: Normalised growth
A12: Food delivery EBITDA margin | B12: 0.055 | C12: 0.055 | D12: 0.058 | E12: 0.06 | F12: 0.062 | G12: 0.065 | H12: Q4 FY26 about 5.5% of NOV
A13: Quick commerce EBITDA margin | B13: 0.003 | C13: 0.01 | D13: 0.015 | E13: 0.02 | F13: 0.025 | G13: 0.04 | H13: Positive but scaling margin
A14: Other EBITDA margin | B14: -0.1 | C14: -0.1 | D14: -0.08 | E14: -0.06 | F14: -0.04 | G14: -0.02 | H14: Losses narrow with scale
A15: Corporate / unallocated costs (₹ cr) | B15: 0 | C15: -200 | D15: -250 | E15: -300 | F15: -350 | G15: -400 | H15: Central costs
A16: Tax rate | B16: 0.25 | C16: 0.25 | D16: 0.25 | E16: 0.25 | F16: 0.25 | G16: 0.25 | H16: Long-term effective cash tax
A17: D&A as % revenue | B17: 0.029 | C17: 0.03 | D17: 0.03 | E17: 0.03 | F17: 0.03 | G17: 0.035 | H17: Infrastructure and intangible amortisation
A18: Capex as % revenue | C18: 0.06 | D18: 0.055 | E18: 0.05 | F18: 0.04 | G18: 0.04 | H18: Dark stores, technology and warehouses
A19: Change in NWC as % incremental revenue | C19: 0.02 | D19: 0.02 | E19: 0.02 | F19: 0.02 | G19: 0.02 | H19: Inventory-led quick commerce
A20: Risk-free rate | B20: 0.0675 | H20: India 10Y government bond yield
A21: Equity risk premium | B21: 0.07 | H21: India ERP assumption
A22: Beta | B22: 1.1 | H22: High-growth consumer internet beta
A23: Pre-tax cost of debt | B23: 0.085 | H23: Illustrative borrowing cost
A24: Debt weight | B24: 0.05 | H24: Illustrative capital structure
A25: Terminal growth rate | B25: 0.05 | H25: Long-term nominal growth
A26: Net cash / (debt) (₹ cr) | B26: 17972 | H26: Cash balance; deduct debt/leases if applicable
A27: Diluted shares (million) | B27: 9650 | H27: Approximate diluted share count
A28: Current share price (₹) | B28: 319.55 | H28: For implied upside comparison

Sheet Revenue Build
A1: Revenue Build
A3: ₹ crore | B3: FY26A | C3: FY27E | D3: FY28E | E3: FY29E | F3: FY30E | G3: FY31E
A4: Food delivery NOV | B4: =Assumptions!B4 | C4: =Assumptions!C4 | D4: =Assumptions!D4 | E4: =Assumptions!E4 | F4: =Assumptions!F4 | G4: =Assumptions!G4
A5: Food delivery growth | B5: =Assumptions!B5 | C5: =Assumptions!C5 | D5: =Assumptions!D5 | E5: =Assumptions!E5 | F5: =Assumptions!F5 | G5: =Assumptions!G5
A6: Food delivery take rate | B6: =Assumptions!B6 | C6: =Assumptions!C6 | D6: =Assumptions!D6 | E6: =Assumptions!E6 | F6: =Assumptions!F6 | G6: =Assumptions!G6
A7: Food delivery revenue | B7: =B4*B6 | C7: =C4*C6 | D7: =D4*D6 | E7: =E4*E6 | F7: =F4*F6 | G7: =G4*G6
A8: Quick commerce NOV | B8: =Assumptions!B7 | C8: =Assumptions!C7 | D8: =Assumptions!D7 | E8: =Assumptions!E7 | F8: =Assumptions!F7 | G8: =Assumptions!G7
A9: Quick commerce growth | B9: =Assumptions!B8 | C9: =Assumptions!C8 | D9: =Assumptions!D8 | E9: =Assumptions!E8 | F9: =Assumptions!F8 | G9: =Assumptions!G8
A10: Quick commerce monetisation | B10: =Assumptions!B9 | C10: =Assumptions!C9 | D10: =Assumptions!D9 | E10: =Assumptions!E9 | F10: =Assumptions!F9 | G10: =Assumptions!G9
A11: Quick commerce revenue | B11: =B8*B10 | C11: =C8*C10 | D11: =D8*D10 | E11: =E8*E10 | F11: =F8*F10 | G11: =G8*G10
A12: Other revenue | B12: =Assumptions!B10 | C12: =Assumptions!C10 | D12: =Assumptions!D10 | E12: =Assumptions!E10 | F12: =Assumptions!F10 | G12: =Assumptions!G10
A13: Other revenue growth | B13: =Assumptions!B11 | C13: =Assumptions!C11 | D13: =Assumptions!D11 | E13: =Assumptions!E11 | F13: =Assumptions!F11 | G13: =Assumptions!G11
A14: Total revenue | B14: =B7+B11+B12 | C14: =C7+C11+C12 | D14: =D7+D11+D12 | E14: =E7+E11+E12 | F14: =F7+F11+F12 | G14: =G7+G11+G12
A15: Total revenue growth | C15: =C14/B14-1 | D15: =D14/C14-1 | E15: =E14/D14-1 | F15: =F14/E14-1 | G15: =G14/F14-1

Sheet Operating Model
A1: EBITDA Bridge & Free Cash Flow
A3: ₹ crore | B3: FY26A | C3: FY27E | D3: FY28E | E3: FY29E | F3: FY30E | G3: FY31E
A4: Food delivery revenue | B4: ='Revenue Build'!B7 | C4: ='Revenue Build'!C7 | D4: ='Revenue Build'!D7 | E4: ='Revenue Build'!E7 | F4: ='Revenue Build'!F7 | G4: ='Revenue Build'!G7
A5: Food delivery EBITDA margin | B5: =Assumptions!B12 | C5: =Assumptions!C12 | D5: =Assumptions!D12 | E5: =Assumptions!E12 | F5: =Assumptions!F12 | G5: =Assumptions!G12
A6: Food delivery EBITDA | B6: =B4*B5 | C6: =C4*C5 | D6: =D4*D5 | E6: =E4*E5 | F6: =F4*F5 | G6: =G4*G5
A7: Quick commerce revenue | B7: ='Revenue Build'!B11 | C7: ='Revenue Build'!C11 | D7: ='Revenue Build'!D11 | E7: ='Revenue Build'!E11 | F7: ='Revenue Build'!F11 | G7: ='Revenue Build'!G11
A8: Quick commerce EBITDA margin | B8: =Assumptions!B13 | C8: =Assumptions!C13 | D8: =Assumptions!D13 | E8: =Assumptions!E13 | F8: =Assumptions!F13 | G8: =Assumptions!G13
A9: Quick commerce EBITDA | B9: =B7*B8 | C9: =C7*C8 | D9: =D7*D8 | E9: =E7*E8 | F9: =F7*F8 | G9: =G7*G8
A10: Other revenue | B10: ='Revenue Build'!B12 | C10: ='Revenue Build'!C12 | D10: ='Revenue Build'!D12 | E10: ='Revenue Build'!E12 | F10: ='Revenue Build'!F12 | G10: ='Revenue Build'!G12
A11: Other EBITDA margin | B11: =Assumptions!B14 | C11: =Assumptions!C14 | D11: =Assumptions!D14 | E11: =Assumptions!E14 | F11: =Assumptions!F14 | G11: =Assumptions!G14
A12: Other EBITDA | B12: =B10*B11 | C12: =C10*C11 | D12: =D10*D11 | E12: =E10*E11 | F12: =F10*F11 | G12: =G10*G11
A13: Corporate / unallocated costs | B13: =Assumptions!B15 | C13: =Assumptions!C15 | D13: =Assumptions!D15 | E13: =Assumptions!E15 | F13: =Assumptions!F15 | G13: =Assumptions!G15
A14: Consolidated EBITDA | B14: =B6+B9+B12+B13 | C14: =C6+C9+C12+C13 | D14: =D6+D9+D12+D13 | E14: =E6+E9+E12+E13 | F14: =F6+F9+F12+F13 | G14: =G6+G9+G12+G13
A15: EBITDA margin | B15: =B14/'Revenue Build'!B14 | C15: =C14/'Revenue Build'!C14 | D15: =D14/'Revenue Build'!D14 | E15: =E14/'Revenue Build'!E14 | F15: =F14/'Revenue Build'!F14 | G15: =G14/'Revenue Build'!G14
A16: D&A | B16: ='Revenue Build'!B14*Assumptions!B17 | C16: ='Revenue Build'!C14*Assumptions!C17 | D16: ='Revenue Build'!D14*Assumptions!D17 | E16: ='Revenue Build'!E14*Assumptions!E17 | F16: ='Revenue Build'!F14*Assumptions!F17 | G16: ='Revenue Build'!G14*Assumptions!G17
A17: EBIT | B17: =B14-B16 | C17: =C14-C16 | D17: =D14-D16 | E17: =E14-E16 | F17: =F14-F16 | G17: =G14-G16
A18: Cash taxes | B18: =MAX(0,B17*Assumptions!B16) | C18: =MAX(0,C17*Assumptions!C16) | D18: =MAX(0,D17*Assumptions!D16) | E18: =MAX(0,E17*Assumptions!E16) | F18: =MAX(0,F17*Assumptions!F16) | G18: =MAX(0,G17*Assumptions!G16)
A19: NOPAT | B19: =B17-B18 | C19: =C17-C18 | D19: =D17-D18 | E19: =E17-E18 | F19: =F17-F18 | G19: =G17-G18
A20: Capex | B20: =-'Revenue Build'!B14*Assumptions!B18 | C20: =-'Revenue Build'!C14*Assumptions!C18 | D20: =-'Revenue Build'!D14*Assumptions!D18 | E20: =-'Revenue Build'!E14*Assumptions!E18 | F20: =-'Revenue Build'!F14*Assumptions!F18 | G20: =-'Revenue Build'!G14*Assumptions!G18
A21: Change in NWC | B21: 0 | C21: =-('Revenue Build'!C14-'Revenue Build'!B14)*Assumptions!C19 | D21: =-('Revenue Build'!D14-'Revenue Build'!C14)*Assumptions!D19 | E21: =-('Revenue Build'!E14-'Revenue Build'!D14)*Assumptions!E19 | F21: =-('Revenue Build'!F14-'Revenue Build'!E14)*Assumptions!F19 | G21: =-('Revenue Build'!G14-'Revenue Build'!F14)*Assumptions!G19
A22: FCFF | B22: =B19+B16+B20+B21 | C22: =C19+C16+C20+C21 | D22: =D19+D16+D20+D21 | E22: =E19+E16+E20+E21 | F22: =F19+F16+F20+F21 | G22: =G19+G16+G20+G21

Sheet DCF
A1: DCF Valuation
A3: ₹ crore | B3: FY26A | C3: FY27E | D3: FY28E | E3: FY29E | F3: FY30E | G3: FY31E
A4: FCFF | B4: ='Operating Model'!B22 | C4: ='Operating Model'!C22 | D4: ='Operating Model'!D22 | E4: ='Operating Model'!E22 | F4: ='Operating Model'!F22 | G4: ='Operating Model'!G22
A5: Discount period | B5: 0 | C5: 1 | D5: 2 | E5: 3 | F5: 4 | G5: 5
A6: Discount factor | C6: =1/(1+$B$13)^C5 | D6: =1/(1+$B$13)^D5 | E6: =1/(1+$B$13)^E5 | F6: =1/(1+$B$13)^F5 | G6: =1/(1+$B$13)^G5
A7: PV of FCFF | C7: =C4*C6 | D7: =D4*D6 | E7: =E4*E6 | F7: =F4*F6 | G7: =G4*G6
A9: Terminal Value
A10: Terminal FCFF | B10: =G4
A11: Terminal value | B11: =B10*(1+Assumptions!B25)/($B$14-Assumptions!B25)
A12: PV of terminal value | B12: =B11*G6
A13: Discount Rate & Valuation
A14: WACC | B14: =(1-Assumptions!B24)*(Assumptions!B20+Assumptions!B21*Assumptions!B22)+Assumptions!B24*Assumptions!B23*(1-Assumptions!B16)
A15: PV of explicit FCFF | B15: =SUM(C7:G7)
A16: Enterprise value | B16: =B15+B12
A17: Net cash / (debt) | B17: =Assumptions!B26
A18: Equity value | B18: =B16+B17
A19: Diluted shares (million) | B19: =Assumptions!B27
A20: DCF value per share | B20: =B18/(B19/100)
A21: Current share price | B21: =Assumptions!B28
A22: Upside / (downside) | B22: =B20/B21-1

Sheet Sensitivity
A1: Sensitivity: DCF Value Per Share
A3: Terminal growth → | B3: 0.04 | C3: 0.05 | D3: 0.06 | E3: 0.07
A4: WACC ↓
A5: 0.12 | B5: =(SUM(DCF!C4/(1+$A5)^1,DCF!D4/(1+$A5)^2,DCF!E4/(1+$A5)^3,DCF!F4/(1+$A5)^4,DCF!G4/(1+$A5)^5)+(DCF!G4*(1+B$3)/($A5-B$3))/(1+$A5)^5+Assumptions!B26)/(Assumptions!B27/100) | C5: =(SUM(DCF!C4/(1+$A5)^1,DCF!D4/(1+$A5)^2,DCF!E4/(1+$A5)^3,DCF!F4/(1+$A5)^4,DCF!G4/(1+$A5)^5)+(DCF!G4*(1+C$3)/($A5-C$3))/(1+$A5)^5+Assumptions!B26)/(Assumptions!B27/100) | D5: =(SUM(DCF!C4/(1+$A5)^1,DCF!D4/(1+$A5)^2,DCF!E4/(1+$A5)^3,DCF!F4/(1+$A5)^4,DCF!G4/(1+$A5)^5)+(DCF!G4*(1+D$3)/($A5-D$3))/(1+$A5)^5+Assumptions!B26)/(Assumptions!B27/100) | E5: =(SUM(DCF!C4/(1+$A5)^1,DCF!D4/(1+$A5)^2,DCF!E4/(1+$A5)^3,DCF!F4/(1+$A5)^4,DCF!G4/(1+$A5)^5)+(DCF!G4*(1+E$3)/($A5-E$3))/(1+$A5)^5+Assumptions!B26)/(Assumptions!B27/100)
A6: 0.13 | B6: =(SUM(DCF!C4/(1+$A6)^1,DCF!D4/(1+$A6)^2,DCF!E4/(1+$A6)^3,DCF!F4/(1+$A6)^4,DCF!G4/(1+$A6)^5)+(DCF!G4*(1+B$3)/($A6-B$3))/(1+$A6)^5+Assumptions!B26)/(Assumptions!B27/100) | C6: =(SUM(DCF!C4/(1+$A6)^1,DCF!D4/(1+$A6)^2,DCF!E4/(1+$A6)^3,DCF!F4/(1+$A6)^4,DCF!G4/(1+$A6)^5)+(DCF!G4*(1+C$3)/($A6-C$3))/(1+$A6)^5+Assumptions!B26)/(Assumptions!B27/100) | D6: =(SUM(DCF!C4/(1+$A6)^1,DCF!D4/(1+$A6)^2,DCF!E4/(1+$A6)^3,DCF!F4/(1+$A6)^4,DCF!G4/(1+$A6)^5)+(DCF!G4*(1+D$3)/($A6-D$3))/(1+$A6)^5+Assumptions!B26)/(Assumptions!B27/100) | E6: =(SUM(DCF!C4/(1+$A6)^1,DCF!D4/(1+$A6)^2,DCF!E4/(1+$A6)^3,DCF!F4/(1+$A6)^4,DCF!G4/(1+$A6)^5)+(DCF!G4*(1+E$3)/($A6-E$3))/(1+$A6)^5+Assumptions!B26)/(Assumptions!B27/100)
A7: 0.1405 | B7: =(SUM(DCF!C4/(1+$A7)^1,DCF!D4/(1+$A7)^2,DCF!E4/(1+$A7)^3,DCF!F4/(1+$A7)^4,DCF!G4/(1+$A7)^5)+(DCF!G4*(1+B$3)/($A7-B$3))/(1+$A7)^5+Assumptions!B26)/(Assumptions!B27/100) | C7: =(SUM(DCF!C4/(1+$A7)^1,DCF!D4/(1+$A7)^2,DCF!E4/(1+$A7)^3,DCF!F4/(1+$A7)^4,DCF!G4/(1+$A7)^5)+(DCF!G4*(1+C$3)/($A7-C$3))/(1+$A7)^5+Assumptions!B26)/(Assumptions!B27/100) | D7: =(SUM(DCF!C4/(1+$A7)^1,DCF!D4/(1+$A7)^2,DCF!E4/(1+$A7)^3,DCF!F4/(1+$A7)^4,DCF!G4/(1+$A7)^5)+(DCF!G4*(1+D$3)/($A7-D$3))/(1+$A7)^5+Assumptions!B26)/(Assumptions!B27/100) | E7: =(SUM(DCF!C4/(1+$A7)^1,DCF!D4/(1+$A7)^2,DCF!E4/(1+$A7)^3,DCF!F4/(1+$A7)^4,DCF!G4/(1+$A7)^5)+(DCF!G4*(1+E$3)/($A7-E$3))/(1+$A7)^5+Assumptions!B26)/(Assumptions!B27/100)
A8: 0.15 | B8: =(SUM(DCF!C4/(1+$A8)^1,DCF!D4/(1+$A8)^2,DCF!E4/(1+$A8)^3,DCF!F4/(1+$A8)^4,DCF!G4/(1+$A8)^5)+(DCF!G4*(1+B$3)/($A8-B$3))/(1+$A8)^5+Assumptions!B26)/(Assumptions!B27/100) | C8: =(SUM(DCF!C4/(1+$A8)^1,DCF!D4/(1+$A8)^2,DCF!E4/(1+$A8)^3,DCF!F4/(1+$A8)^4,DCF!G4/(1+$A8)^5)+(DCF!G4*(1+C$3)/($A8-C$3))/(1+$A8)^5+Assumptions!B26)/(Assumptions!B27/100) | D8: =(SUM(DCF!C4/(1+$A8)^1,DCF!D4/(1+$A8)^2,DCF!E4/(1+$A8)^3,DCF!F4/(1+$A8)^4,DCF!G4/(1+$A8)^5)+(DCF!G4*(1+D$3)/($A8-D$3))/(1+$A8)^5+Assumptions!B26)/(Assumptions!B27/100) | E8: =(SUM(DCF!C4/(1+$A8)^1,DCF!D4/(1+$A8)^2,DCF!E4/(1+$A8)^3,DCF!F4/(1+$A8)^4,DCF!G4/(1+$A8)^5)+(DCF!G4*(1+E$3)/($A8-E$3))/(1+$A8)^5+Assumptions!B26)/(Assumptions!B27/100)
A9: 0.16 | B9: =(SUM(DCF!C4/(1+$A9)^1,DCF!D4/(1+$A9)^2,DCF!E4/(1+$A9)^3,DCF!F4/(1+$A9)^4,DCF!G4/(1+$A9)^5)+(DCF!G4*(1+B$3)/($A9-B$3))/(1+$A9)^5+Assumptions!B26)/(Assumptions!B27/100) | C9: =(SUM(DCF!C4/(1+$A9)^1,DCF!D4/(1+$A9)^2,DCF!E4/(1+$A9)^3,DCF!F4/(1+$A9)^4,DCF!G4/(1+$A9)^5)+(DCF!G4*(1+C$3)/($A9-C$3))/(1+$A9)^5+Assumptions!B26)/(Assumptions!B27/100) | D9: =(SUM(DCF!C4/(1+$A9)^1,DCF!D4/(1+$A9)^2,DCF!E4/(1+$A9)^3,DCF!F4/(1+$A9)^4,DCF!G4/(1+$A9)^5)+(DCF!G4*(1+D$3)/($A9-D$3))/(1+$A9)^5+Assumptions!B26)/(Assumptions!B27/100) | E9: =(SUM(DCF!C4/(1+$A9)^1,DCF!D4/(1+$A9)^2,DCF!E4/(1+$A9)^3,DCF!F4/(1+$A9)^4,DCF!G4/(1+$A9)^5)+(DCF!G4*(1+E$3)/($A9-E$3))/(1+$A9)^5+Assumptions!B26)/(Assumptions!B27/100)
A12: Interpretation
A13: Higher terminal growth and lower WACC increase the DCF value per share. The model is intentionally transparent: users can replace operating assumptions with company disclosures or research estimates.
